fzutility/__init__.py
fzutility/logger.py
fzutility/mqttclient.py
fzutility-1.0.6.dist-info/METADATA
fzutility-1.0.6.dist-info/WHEEL
fzutility-1.0.6.dist-info/top_level.txt
fzutility-1.0.6.dist-info/RECORD
