Metadata-Version: 2.1
Name: fzutility
Version: 1.0.6
Summary: fzutility is a package that provides various utilities for python programming.
Home-page: 
Author: dnchoi
Author-email: luke.dn.choi@funzin.co.kr
License: MIT
Requires-Python: >=3.6
Requires-Dist: black
Requires-Dist: flake8
Requires-Dist: colorlog
Requires-Dist: paho-mqtt ==1.5.1
